nonebot_plugin_pallas_repeater/__init__.py
nonebot_plugin_pallas_repeater/config.py
nonebot_plugin_pallas_repeater/block/__init__.py
nonebot_plugin_pallas_repeater/drink/__init__.py
nonebot_plugin_pallas_repeater/repeater/__init__.py
nonebot_plugin_pallas_repeater/repeater/model.py
nonebot_plugin_pallas_repeater/take_name/__init__.py
nonebot_plugin_pallas_repeater/utils/__init__.py
nonebot_plugin_pallas_repeater/utils/array2cqcode/__init__.py
nonebot_plugin_pallas_repeater/utils/array2cqcode/message_segment.py
nonebot_plugin_pallas_repeater/utils/media_cache/__init__.py
nonebot_plugin_pallas_repeater-0.1.4.dist-info/LICENSE
nonebot_plugin_pallas_repeater-0.1.4.dist-info/METADATA
nonebot_plugin_pallas_repeater-0.1.4.dist-info/WHEEL
nonebot_plugin_pallas_repeater-0.1.4.dist-info/top_level.txt
nonebot_plugin_pallas_repeater-0.1.4.dist-info/RECORD
