Metadata-Version: 2.1
Name: nonebot_plugin_pallas_repeater
Version: 0.1.4
Summary: nonebot-plugin-pallas-repeater
Home-page: https://github.com/Redmomn/nonebot-plugin-pallas-repeater
Author: Redmomn
Author-email: 109732988+Redmomn@users.noreply.github.com
License: AGPL-3.0
Keywords: nonebot2,repeater
License-File: LICENSE
Requires-Dist: nonebot-adapter-onebot >=2.0.0
Requires-Dist: nonebot2 >=2.0.0
Requires-Dist: nonebot2[httpx]
Requires-Dist: nonebot-plugin-apscheduler
Requires-Dist: pypinyin
Requires-Dist: pymongo
Requires-Dist: jieba
